uzdabrawza/__init__.py
uzdabrawza/cli.py
uzdabrawza/core.py
uzdabrawza-1.0.3.dist-info/METADATA
uzdabrawza-1.0.3.dist-info/WHEEL
uzdabrawza-1.0.3.dist-info/entry_points.txt
uzdabrawza-1.0.3.dist-info/licenses/LICENSE
uzdabrawza-1.0.3.dist-info/RECORD
