Metadata-Version: 2.4
Name: uzdabrawza
Version: 1.0.3
Summary: The Anal-Queen of AI Browser Automation - A beautifully fucked-up browser automation script that actually works
Project-URL: Homepage, https://github.com/psyb0t/uzdabrawza
Project-URL: Documentation, https://github.com/psyb0t/uzdabrawza#readme
Project-URL: Repository, https://github.com/psyb0t/uzdabrawza.git
Project-URL: Bug Tracker, https://github.com/psyb0t/uzdabrawza/issues
Project-URL: Changelog, https://github.com/psyb0t/uzdabrawza/blob/main/CHANGELOG.md
Author-email: uzdabrawza <uzdabrawza@example.com>
Maintainer-email: uzdabrawza <uzdabrawza@example.com>
License:         DO WHAT THE FUCK YOU WANT TO PUBLIC LICENSE
License-File: LICENSE
Keywords: ai-automation,automation,bot-detection,browser-automation,browser-use,llm,patchright,playwright,scraping,stealth,web-scraping
Classifier: Development Status :: 5 - Production/Stable
Classifier: Environment :: Console
Classifier: Intended Audience :: Developers
Classifier: Intended Audience :: Information Technology
Classifier: License :: OSI Approved :: MIT License
Classifier: Operating System :: OS Independent
Classifier: Programming Language :: Python :: 3
Classifier: Programming Language :: Python :: 3.11
Classifier: Programming Language :: Python :: 3.12
Classifier: Programming Language :: Python :: 3.13
Classifier: Topic :: Internet :: WWW/HTTP :: Browsers
Classifier: Topic :: Software Development :: Libraries :: Python Modules
Classifier: Topic :: Software Development :: Quality Assurance
Classifier: Topic :: Software Development :: Testing
Classifier: Topic :: System :: Networking
Classifier: Topic :: Utilities
Requires-Python: >=3.11
Requires-Dist: browser-use>=0.1.0
Requires-Dist: patchright>=1.0.0
Requires-Dist: pillow>=9.0.0
Requires-Dist: python-dotenv>=1.0.0
Provides-Extra: build
Requires-Dist: build>=1.0.0; extra == 'build'
Requires-Dist: hatchling>=1.21.0; extra == 'build'
Requires-Dist: twine>=4.0.0; extra == 'build'
